mc_postgres_db/__init__.py
mc_postgres_db/models.py
mc_postgres_db/operations.py
mc_postgres_db/prefect/__init__.py
mc_postgres_db/prefect/tasks.py
mc_postgres_db/prefect/asyncio/__init__.py
mc_postgres_db/prefect/asyncio/tasks.py
mc_postgres_db/testing/__init__.py
mc_postgres_db/testing/utilities.py
mc_postgres_db-1.4.3.dist-info/METADATA
mc_postgres_db-1.4.3.dist-info/WHEEL
mc_postgres_db-1.4.3.dist-info/top_level.txt
mc_postgres_db-1.4.3.dist-info/RECORD
