Metadata-Version: 2.4
Name: mc-postgres-db
Version: 1.4.3
Summary: Add your description here
Requires-Python: >=3.12
Requires-Dist: alembic>=1.16.2
Requires-Dist: pandas>=2.3.1
Requires-Dist: prefect>=3.4.8
Requires-Dist: psycopg2-binary>=2.9.10
Requires-Dist: ruff>=0.12.0
Requires-Dist: sqlalchemy>=2.0.41
